dl_personal_biography/__init__.py
dl_personal_biography/core.py
dl_personal_biography/log.py
dl_personal_biography/server.py
dl_personal_biography-0.1.1.dist-info/METADATA
dl_personal_biography-0.1.1.dist-info/WHEEL
dl_personal_biography-0.1.1.dist-info/top_level.txt
dl_personal_biography-0.1.1.dist-info/RECORD
